LICENSE
einsteinify/.gitignore
einsteinify/__init__.py
einsteinify/__main__.py
einsteinify/einsteinify.py
einsteinify-1.1.1.dist-info/entry_points.txt
einsteinify-1.1.1.dist-info/LICENSE
einsteinify-1.1.1.dist-info/WHEEL
einsteinify-1.1.1.dist-info/METADATA
einsteinify-1.1.1.dist-info/RECORD
